{
  "$schema": "https://ui.shadcn.com/schema/registry-item.json",
  "name": "pixel-canvas",
  "title": "Pixel Canvas",
  "author": "designbycode",
  "dependencies": [],
  "registryDependencies": [],
  "files": [
    {
      "path": "resources/js/registry/new-york/components/ui/canvas/pixel-canvas.tsx",
      "content": "'use client';\n\nimport { useEffect, useRef } from 'react';\n\ntype PixelType = {\n    x: number;\n    y: number;\n    color: string;\n    size: number;\n    speed: number;\n    sizeStep: number;\n    minSize: number;\n    maxSize: number;\n    delay: number;\n    counter: number;\n    counterStep: number;\n    isIdle: boolean;\n    isReverse: boolean;\n    isShimmer: boolean;\n};\n\nfunction getRandom(min: number, max: number) {\n    return Math.random() * (max - min) + min;\n}\n\nexport function PixelCanvas({\n    colors = ['#f8fafc', '#f1f5f9', '#cbd5e1'],\n    gap = 5,\n    speed = 35,\n    noFocus = false,\n    className,\n}: {\n    colors?: string[];\n    gap?: number;\n    speed?: number;\n    noFocus?: boolean;\n    className?: string;\n}) {\n    const canvasRef = useRef<HTMLCanvasElement | null>(null);\n    const pixelsRef = useRef<PixelType[]>([]);\n    const animationRef = useRef<number>(0);\n    const parentRef = useRef<HTMLDivElement | null>(null);\n\n    const timePrevious = useRef(performance.now());\n    const timeInterval = 1000 / 60;\n\n    const reducedMotion =\n        typeof window !== 'undefined' &&\n        window.matchMedia('(prefers-reduced-motion: reduce)').matches;\n\n    const normalizedGap = Math.min(Math.max(gap, 4), 50);\n\n    const normalizedSpeed = (() => {\n        const throttle = 0.001;\n\n        if (speed <= 0 || reducedMotion) {\nreturn 0;\n}\n\n        if (speed >= 100) {\nreturn 100 * throttle;\n}\n\n        return speed * throttle;\n    })();\n\n    const getDistanceToCenter = (\n        canvas: HTMLCanvasElement,\n        x: number,\n        y: number,\n    ) => {\n        const dx = x - canvas.width / 2;\n        const dy = y - canvas.height / 2;\n\n        return Math.sqrt(dx * dx + dy * dy);\n    };\n\n    const createPixels = (\n        canvas: HTMLCanvasElement,\n        ctx: CanvasRenderingContext2D,\n    ) => {\n        const pixels: PixelType[] = [];\n\n        for (let x = 0; x < canvas.width; x += normalizedGap) {\n            for (let y = 0; y < canvas.height; y += normalizedGap) {\n                const color = colors[Math.floor(Math.random() * colors.length)];\n                const delay = reducedMotion\n                    ? 0\n                    : getDistanceToCenter(canvas, x, y);\n\n                pixels.push({\n                    x,\n                    y,\n                    color,\n                    size: 0,\n                    speed: getRandom(0.1, 0.9) * normalizedSpeed,\n                    sizeStep: Math.random() * 0.4,\n                    minSize: 0.5,\n                    maxSize: getRandom(0.5, 2),\n                    delay,\n                    counter: 0,\n                    counterStep:\n                        Math.random() * 4 +\n                        (canvas.width + canvas.height) * 0.01,\n                    isIdle: false,\n                    isReverse: false,\n                    isShimmer: false,\n                });\n            }\n        }\n\n        pixelsRef.current = pixels;\n    };\n\n    const draw = (ctx: CanvasRenderingContext2D, p: PixelType) => {\n        const centerOffset = 1 - p.size * 0.5;\n\n        ctx.fillStyle = p.color;\n        ctx.fillRect(p.x + centerOffset, p.y + centerOffset, p.size, p.size);\n    };\n\n    const shimmer = (p: PixelType) => {\n        if (p.size >= p.maxSize) {\np.isReverse = true;\n} else if (p.size <= p.minSize) {\np.isReverse = false;\n}\n\n        p.size += p.isReverse ? -p.speed : p.speed;\n    };\n\n    const appear = (ctx: CanvasRenderingContext2D, p: PixelType) => {\n        p.isIdle = false;\n\n        if (p.counter <= p.delay) {\n            p.counter += p.counterStep;\n\n            return;\n        }\n\n        if (p.size >= p.maxSize) {\n            p.isShimmer = true;\n        }\n\n        if (p.isShimmer) {\n            shimmer(p);\n        } else {\n            p.size += p.sizeStep;\n        }\n\n        draw(ctx, p);\n    };\n\n    const disappear = (ctx: CanvasRenderingContext2D, p: PixelType) => {\n        p.isShimmer = false;\n        p.counter = 0;\n\n        if (p.size <= 0) {\n            p.isIdle = true;\n\n            return;\n        }\n\n        p.size -= 0.1;\n        draw(ctx, p);\n    };\n\n    const animate = (\n        ctx: CanvasRenderingContext2D,\n        canvas: HTMLCanvasElement,\n        mode: 'appear' | 'disappear',\n    ) => {\n        animationRef.current = requestAnimationFrame(() =>\n            animate(ctx, canvas, mode),\n        );\n\n        const now = performance.now();\n        const delta = now - timePrevious.current;\n\n        if (delta < timeInterval) {\nreturn;\n}\n\n        timePrevious.current = now - (delta % timeInterval);\n\n        ctx.clearRect(0, 0, canvas.width, canvas.height);\n\n        pixelsRef.current.forEach((p) => {\n            mode === 'appear' ? appear(ctx, p) : disappear(ctx, p);\n        });\n\n        if (pixelsRef.current.every((p) => p.isIdle)) {\n            cancelAnimationFrame(animationRef.current);\n        }\n    };\n\n    const init = () => {\n        const canvas = canvasRef.current;\n\n        if (!canvas) {\nreturn;\n}\n\n        const rect = canvas.getBoundingClientRect();\n        const width = Math.floor(rect.width);\n        const height = Math.floor(rect.height);\n\n        canvas.width = width;\n        canvas.height = height;\n\n        const ctx = canvas.getContext('2d');\n\n        if (!ctx) {\nreturn;\n}\n\n        createPixels(canvas, ctx);\n    };\n\n    useEffect(() => {\n        init();\n\n        const resizeObserver = new ResizeObserver(init);\n\n        if (canvasRef.current) {\nresizeObserver.observe(canvasRef.current);\n}\n\n        return () => resizeObserver.disconnect();\n    }, []);\n\n    useEffect(() => {\n        const parent = parentRef.current;\n        const canvas = canvasRef.current;\n\n        if (!parent || !canvas) {\nreturn;\n}\n\n        const ctx = canvas.getContext('2d');\n\n        if (!ctx) {\nreturn;\n}\n\n        const handleEnter = () => {\n            cancelAnimationFrame(animationRef.current);\n            animate(ctx, canvas, 'appear');\n        };\n\n        const handleLeave = () => {\n            cancelAnimationFrame(animationRef.current);\n            animate(ctx, canvas, 'disappear');\n        };\n\n        parent.addEventListener('mouseenter', handleEnter);\n        parent.addEventListener('mouseleave', handleLeave);\n\n        if (!noFocus) {\n            parent.addEventListener('focusin', handleEnter);\n            parent.addEventListener('focusout', handleLeave);\n        }\n\n        return () => {\n            parent.removeEventListener('mouseenter', handleEnter);\n            parent.removeEventListener('mouseleave', handleLeave);\n            parent.removeEventListener('focusin', handleEnter);\n            parent.removeEventListener('focusout', handleLeave);\n        };\n    }, [noFocus]);\n\n    return (\n        <div ref={parentRef} className={className}>\n            <canvas ref={canvasRef} className=\"block h-full w-full\" />\n        </div>\n    );\n}\n",
      "type": "registry:ui"
    }
  ],
  "meta": {
    "category": "components",
    "version": "1.0.0"
  },
  "type": "registry:ui"
}